{
  "": "",
  "Decrement": "Decrement",
  "Increment": "Increment",
  "Profile page": "Profile page",
  "throw Error": "throw Error",
  "throw;": "throw;",
  "Ваш возраст": "Ваш возраст",
  "Ваш город": "Ваш город",
  "Ваша страна": "Ваша страна",
  "Ваша фамилия": "",
  "Ваше изображение профиля": "Ваше изображение профиля",
  "Ваше имя": "",
  "Ваше пользовательское имя": "Ваше пользовательское имя",
  "Введите имя": "Введите имя",
  "Введите имя пользователя": "",
  "Введите пароль": "",
  "Введите текст": "",
  "Войти": "",
  "Вы ввели неверный логин или пароль": "",
  "Выйти": "Выйти",
  "Главная": "",
  "Главная страница": "Главная страница",
  "О сайте": "О сайте",
  "Обновить страницу": "Обновить страницу",
  "Отменить": "Отменить",
  "Попробуйте обновить страницу": "",
  "Произошла непредвиденная ошибка": "Произошла непредвиденная ошибка",
  "Произошла непредвиденная ошибка при загрузке профиля": "",
  "Профиль": "Профиль",
  "Редактировать": "Редактировать",
  "Сохранить": "Сохранить",
  "Страница не найдена": "Страница не найдена",
  "Укажите валюту": "",
  "Укажите страну": "",
  "Форма авторизации": "",
  "Язык": "Язык"
}
